yayarl/__init__.py
yayarl/_parse.py
yayarl/_path.py
yayarl/_query.py
yayarl/_quoters.py
yayarl/_quoting.py
yayarl/_quoting_c.cpython-313-x86_64-linux-gnu.so
yayarl/_quoting_py.py
yayarl/_requests.py
yayarl/_url.py
yayarl/py.typed
yayarl-2.2.1.dist-info/licenses/LICENSE
yayarl-2.2.1.dist-info/METADATA
yayarl-2.2.1.dist-info/WHEEL
yayarl-2.2.1.dist-info/top_level.txt
yayarl-2.2.1.dist-info/RECORD
