Metadata-Version: 2.4
Name: yayarl
Version: 2.2.1
Summary: "Yet another YARL"; A fork with `requests` integration
Home-page: https://github.com/robinvandernoord/yayarl
Author: Robin van der Noord
Author-email: robin@trialandsuccess.nl
Maintainer: Robin van der Noord <team@aiohttp.org>
Maintainer-email: robin@trialandsuccess.nl
License: Apache-2.0
Project-URL: Chat: Matrix, https://matrix.to/#/#robinvandernoord-space:matrix.org
Project-URL: CI: GitHub Workflows, https://github.com/robinvandernoord/yayarl/actions?query=branch:master
Project-URL: Code of Conduct, https://github.com/robinvandernoord/.github/blob/master/CODE_OF_CONDUCT.md
Project-URL: Coverage: codecov, https://codecov.io/github/robinvandernoord/yayarl
Project-URL: Docs: Changelog, https://github.com/robinvandernoord/yayarl/blob/master/CHANGES.rst#changelog
Project-URL: Docs: RTD, https://yarl.aio-libs.org
Project-URL: GitHub: issues, https://github.com/robinvandernoord/yayarl/issues
Project-URL: GitHub: repo, https://github.com/robinvandernoord/yayarl
Keywords: cython,cext,yarl,yayarl
Classifier: Development Status :: 5 - Production/Stable
Classifier: Intended Audience :: Developers
Classifier: License :: OSI Approved :: Apache Software License
Classifier: Programming Language :: Cython
Classifier: Programming Language :: Python
Classifier: Programming Language :: Python :: 3
Classifier: Programming Language :: Python :: 3.10
Classifier: Programming Language :: Python :: 3.11
Classifier: Programming Language :: Python :: 3.12
Classifier: Programming Language :: Python :: 3.13
Classifier: Topic :: Internet :: WWW/HTTP
Classifier: Topic :: Software Development :: Libraries :: Python Modules
Requires-Python: >=3.11
License-File: LICENSE
Requires-Dist: idna>=2.0
Requires-Dist: multidict>=4.0
Requires-Dist: propcache>=0.2.1
Requires-Dist: typing-extensions>=3.7.4; python_version < "3.8"
Requires-Dist: requests~=2.32.0
Dynamic: license-file
